Metadata-Version: 1.1
Name: slack-jirer
Version: 1.0
Summary: Slack JIRA URL expander
Home-page: https://github.com/kotnik/slack-jirer
Author: Nikola Kotur
Author-email: kotnick@gmail.com
License: UNKNOWN
Download-URL: https://github.com/kotnik/slack-jirer/archive/1.0.zip
Platform: UNKNOWN
Classifier: Programming Language :: Python
